pytest_notebook/__init__.py
pytest_notebook/diffing.py
pytest_notebook/execution.py
pytest_notebook/ipy_magic.py
pytest_notebook/nb_regression.py
pytest_notebook/notebook.py
pytest_notebook/plugin.py
pytest_notebook/post_processors.py
pytest_notebook/utils.py
pytest_notebook/example_nbs/__init__.py
pytest_notebook/example_nbs/coverage.ipynb
pytest_notebook/example_nbs/example1.ipynb
pytest_notebook/example_nbs/example1_pass.ipynb
pytest_notebook/example_nbs/example2.ipynb
pytest_notebook/resources/__init__.py
pytest_notebook/resources/nb_metadata.schema.json
pytest_notebook-0.10.0.dist-info/entry_points.txt
pytest_notebook-0.10.0.dist-info/LICENSE
pytest_notebook-0.10.0.dist-info/WHEEL
pytest_notebook-0.10.0.dist-info/METADATA
pytest_notebook-0.10.0.dist-info/RECORD
