Metadata-Version: 2.1
Name: pytest_notebook
Version: 0.10.0
Summary: A pytest plugin for testing Jupyter Notebooks.
Author-email: Chris Sewell <chrisj_sewell@hotmail.com>
Requires-Python: ~=3.8
Classifier: Development Status :: 4 - Beta
Classifier: Framework :: Pytest
Classifier: Intended Audience :: Developers
Classifier: Topic :: Software Development :: Testing
Classifier: Programming Language :: Python
Classifier: Programming Language :: Python :: 3
Classifier: Programming Language :: Python :: 3.8
Classifier: Programming Language :: Python :: 3.9
Classifier: Programming Language :: Python :: 3.10
Classifier: Programming Language :: Python :: 3.11
Classifier: Programming Language :: Python :: 3.12
Classifier: Programming Language :: Python :: Implementation :: CPython
Classifier: Operating System :: OS Independent
Classifier: License :: OSI Approved :: BSD License
Requires-Dist: pytest>=3.5.0
Requires-Dist: attrs<23,>=19
Requires-Dist: importlib-metadata~=6.0;python_version<'3.10'
Requires-Dist: importlib-resources~=5.0;python_version<'3.9'
Requires-Dist: nbclient~=0.5.10
Requires-Dist: nbdime>=4
Requires-Dist: nbformat
Requires-Dist: jsonschema
Requires-Dist: pre-commit~=3.5.0 ; extra == "code_style"
Requires-Dist: doc8<0.9.0,>=0.8.0 ; extra == "code_style"
Requires-Dist: sphinx>=3 ; extra == "docs"
Requires-Dist: pyyaml ; extra == "docs"
Requires-Dist: sphinx-book-theme~=1.0.1 ; extra == "docs"
Requires-Dist: myst-nb~=1.0 ; extra == "docs"
Requires-Dist: coverage~=5.0 ; extra == "docs"
Requires-Dist: pytest-cov ; extra == "docs"
Requires-Dist: black ; extra == "docs"
Requires-Dist: pytest-cov ; extra == "testing"
Requires-Dist: pytest-regressions ; extra == "testing"
Requires-Dist: ipykernel ; extra == "testing"
Requires-Dist: coverage~=5.0 ; extra == "testing"
Requires-Dist: black==23.11.0 ; extra == "testing"
Requires-Dist: beautifulsoup4==4.12.2 ; extra == "testing"
Project-URL: Documentation, https://pytest-notebook.readthedocs.io
Project-URL: Source, https://github.com/chrisjsewell/pytest-notebook
Provides-Extra: code_style
Provides-Extra: docs
Provides-Extra: testing
